{
  "dataFields": [
    {
      "Id": 5268,
      "Name": "creator",
      "ShowName": "录入者",
      "Type": "local",
      "ContentType": "ShortText",
      "DictKeyId": null,
      "Options": null,
      "IsMultiple": "no",
      "IsRepeat": "yes",
      "DataType": "ShortString",
      "BindDataField": "ShortString042",
      "Abbreviation": null,
      "Placeholder": null,
      "Unit": null,
      "Description": null,
      "SortOrder": 5268,
      "OperateAuthority": "create,edit,editShow,pagerShow",
      "IsRequired": "no",
      "DataSource": null,
      "DefaultValue": null,
      "IsSearch": "no",
      "IsUnifySearch": "no",
      "GroupType": "channel",
      "GroupId": 3123,
      "CreateIp": "127.0.0.1",
      "CreateBy": 172,
      "CreateTime": "2021-12-21T15:46:52",
      "IsDeleted": "undeleted",
      "SiteId": 1
    },
    {
      "Id": 5269,
      "Name": "title",
      "ShowName": "书名",
      "Type": "local",
      "ContentType": "MiddleText",
      "DictKeyId": null,
      "Options": null,
      "IsMultiple": "no",
      "IsRepeat": "yes",
      "DataType": "MiddleString",
      "BindDataField": "MiddleString001",
      "Abbreviation": null,
      "Placeholder": null,
      "Unit": null,
      "Description": "文章标题",
      "SortOrder": 5269,
      "OperateAuthority": "create,edit,editShow,pagerShow",
      "IsRequired": "yes",
      "DataSource": null,
      "DefaultValue": null,
      "IsSearch": "yes",
      "IsUnifySearch": "yes",
      "GroupType": "channel",
      "GroupId": 3123,
      "CreateIp": "127.0.0.1",
      "CreateBy": 172,
      "CreateTime": "2021-12-21T15:47:22",
      "IsDeleted": "undeleted",
      "SiteId": 1
    },
    {
      "Id": 5270,
      "Name": "author",
      "ShowName": "主要责任者",
      "Type": "local",
      "ContentType": "MiddleText",
      "DictKeyId": null,
      "Options": null,
      "IsMultiple": "no",
      "IsRepeat": "yes",
      "DataType": "MiddleString",
      "BindDataField": "MiddleString002",
      "Abbreviation": null,
      "Placeholder": null,
      "Unit": null,
      "Description": null,
      "SortOrder": 5270,
      "OperateAuthority": "create,edit,editShow,pagerShow",
      "IsRequired": "no",
      "DataSource": null,
      "DefaultValue": null,
      "IsSearch": "yes",
      "IsUnifySearch": "yes",
      "GroupType": "channel",
      "GroupId": 3123,
      "CreateIp": "127.0.0.1",
      "CreateBy": 172,
      "CreateTime": "2021-12-21T15:48:01",
      "IsDeleted": "undeleted",
      "SiteId": 1
    },
    {
      "Id": 5271,
      "Name": "number",
      "ShowName": "唯一编号",
      "Type": "local",
      "ContentType": "ShortText",
      "DictKeyId": null,
      "Options": null,
      "IsMultiple": "no",
      "IsRepeat": "yes",
      "DataType": "ShortString",
      "BindDataField": "ShortString001",
      "Abbreviation": null,
      "Placeholder": null,
      "Unit": null,
      "Description": "唯一标识",
      "SortOrder": 5271,
      "OperateAuthority": "create,edit,editShow",
      "IsRequired": "yes",
      "DataSource": null,
      "DefaultValue": null,
      "IsSearch": "no",
      "IsUnifySearch": "no",
      "GroupType": "channel",
      "GroupId": 3123,
      "CreateIp": "127.0.0.1",
      "CreateBy": 172,
      "CreateTime": "2021-12-21T15:52:31",
      "IsDeleted": "undeleted",
      "SiteId": 1
    },
    {
      "Id": 5272,
      "Name": "totalnum",
      "ShowName": "总号",
      "Type": "local",
      "ContentType": "ShortText",
      "DictKeyId": null,
      "Options": null,
      "IsMultiple": "no",
      "IsRepeat": "yes",
      "DataType": "ShortString",
      "BindDataField": "ShortString078",
      "Abbreviation": null,
      "Placeholder": null,
      "Unit": null,
      "Description": null,
      "SortOrder": 5272,
      "OperateAuthority": "create,edit,editShow",
      "IsRequired": "no",
      "DataSource": null,
      "DefaultValue": null,
      "IsSearch": "no",
      "IsUnifySearch": "no",
      "GroupType": "channel",
      "GroupId": 3123,
      "CreateIp": "127.0.0.1",
      "CreateBy": 172,
      "CreateTime": "2021-12-21T15:53:12",
      "IsDeleted": "undeleted",
      "SiteId": 1
    },
    {
      "Id": 5273,
      "Name": "callnum",
      "ShowName": "索书号",
      "Type": "local",
      "ContentType": "ShortText",
      "DictKeyId": null,
      "Options": null,
      "IsMultiple": "no",
      "IsRepeat": "yes",
      "DataType": "ShortString",
      "BindDataField": "ShortString079",
      "Abbreviation": null,
      "Placeholder": null,
      "Unit": null,
      "Description": null,
      "SortOrder": 5273,
      "OperateAuthority": "create,edit,editShow",
      "IsRequired": "no",
      "DataSource": null,
      "DefaultValue": null,
      "IsSearch": "no",
      "IsUnifySearch": "no",
      "GroupType": "channel",
      "GroupId": 3123,
      "CreateIp": "127.0.0.1",
      "CreateBy": 172,
      "CreateTime": "2021-12-21T16:25:59",
      "IsDeleted": "undeleted",
      "SiteId": 1
    },
    {
      "Id": 5274,
      "Name": "docNo",
      "ShowName": "古籍普查编号",
      "Type": "local",
      "ContentType": "ShortText",
      "DictKeyId": null,
      "Options": null,
      "IsMultiple": "no",
      "IsRepeat": "yes",
      "DataType": "ShortString",
      "BindDataField": "ShortString080",
      "Abbreviation": null,
      "Placeholder": null,
      "Unit": null,
      "Description": null,
      "SortOrder": 5274,
      "OperateAuthority": "create,edit,editShow",
      "IsRequired": "no",
      "DataSource": null,
      "DefaultValue": null,
      "IsSearch": "no",
      "IsUnifySearch": "no",
      "GroupType": "channel",
      "GroupId": 3123,
      "CreateIp": "127.0.0.1",
      "CreateBy": 172,
      "CreateTime": "2021-12-21T16:26:48",
      "IsDeleted": "undeleted",
      "SiteId": 1
    },
    {
      "Id": 5275,
      "Name": "class",
      "ShowName": "四部分类",
      "Type": "local",
      "ContentType": "ShortText",
      "DictKeyId": null,
      "Options": null,
      "IsMultiple": "no",
      "IsRepeat": "yes",
      "DataType": "ShortString",
      "BindDataField": "ShortString024",
      "Abbreviation": null,
      "Placeholder": null,
      "Unit": null,
      "Description": null,
      "SortOrder": 5275,
      "OperateAuthority": "create,edit,editShow,pagerShow",
      "IsRequired": "no",
      "DataSource": null,
      "DefaultValue": null,
      "IsSearch": "no",
      "IsUnifySearch": "no",
      "GroupType": "channel",
      "GroupId": 3123,
      "CreateIp": "127.0.0.1",
      "CreateBy": 172,
      "CreateTime": "2021-12-21T16:27:42",
      "IsDeleted": "undeleted",
      "SiteId": 1
    },
    {
      "Id": 5276,
      "Name": "age",
      "ShowName": "年代",
      "Type": "local",
      "ContentType": "ShortText",
      "DictKeyId": null,
      "Options": null,
      "IsMultiple": "no",
      "IsRepeat": "yes",
      "DataType": "ShortString",
      "BindDataField": "ShortString081",
      "Abbreviation": null,
      "Placeholder": null,
      "Unit": null,
      "Description": null,
      "SortOrder": 5276,
      "OperateAuthority": "create,edit,editShow",
      "IsRequired": "no",
      "DataSource": null,
      "DefaultValue": null,
      "IsSearch": "no",
      "IsUnifySearch": "no",
      "GroupType": "channel",
      "GroupId": 3123,
      "CreateIp": "127.0.0.1",
      "CreateBy": 172,
      "CreateTime": "2021-12-21T16:28:28",
      "IsDeleted": "undeleted",
      "SiteId": 1
    },
    {
      "Id": 5277,
      "Name": "version",
      "ShowName": "版本（带补配）",
      "Type": "local",
      "ContentType": "ShortText",
      "DictKeyId": null,
      "Options": null,
      "IsMultiple": "no",
      "IsRepeat": "yes",
      "DataType": "ShortString",
      "BindDataField": "ShortString082",
      "Abbreviation": null,
      "Placeholder": null,
      "Unit": null,
      "Description": null,
      "SortOrder": 5277,
      "OperateAuthority": "create,edit,editShow,pagerShow",
      "IsRequired": "no",
      "DataSource": null,
      "DefaultValue": null,
      "IsSearch": "no",
      "IsUnifySearch": "no",
      "GroupType": "channel",
      "GroupId": 3123,
      "CreateIp": "127.0.0.1",
      "CreateBy": 172,
      "CreateTime": "2021-12-21T16:29:47",
      "IsDeleted": "undeleted",
      "SiteId": 1
    },
    {
      "Id": 5278,
      "Name": "vol",
      "ShowName": "卷",
      "Type": "local",
      "ContentType": "ShortText",
      "DictKeyId": null,
      "Options": null,
      "IsMultiple": "no",
      "IsRepeat": "yes",
      "DataType": "ShortString",
      "BindDataField": "ShortString013",
      "Abbreviation": null,
      "Placeholder": null,
      "Unit": null,
      "Description": null,
      "SortOrder": 5278,
      "OperateAuthority": "create,edit,editShow",
      "IsRequired": "no",
      "DataSource": null,
      "DefaultValue": null,
      "IsSearch": "no",
      "IsUnifySearch": "no",
      "GroupType": "channel",
      "GroupId": 3123,
      "CreateIp": "127.0.0.1",
      "CreateBy": 172,
      "CreateTime": "2021-12-21T16:30:17",
      "IsDeleted": "undeleted",
      "SiteId": 1
    },
    {
      "Id": 5279,
      "Name": "copiesCount",
      "ShowName": "册数",
      "Type": "local",
      "ContentType": "ShortText",
      "DictKeyId": null,
      "Options": null,
      "IsMultiple": "no",
      "IsRepeat": "yes",
      "DataType": "ShortString",
      "BindDataField": "ShortString083",
      "Abbreviation": null,
      "Placeholder": null,
      "Unit": null,
      "Description": null,
      "SortOrder": 5279,
      "OperateAuthority": "create,edit,editShow,pagerShow",
      "IsRequired": "no",
      "DataSource": null,
      "DefaultValue": null,
      "IsSearch": "no",
      "IsUnifySearch": "no",
      "GroupType": "channel",
      "GroupId": 3123,
      "CreateIp": "127.0.0.1",
      "CreateBy": 172,
      "CreateTime": "2021-12-21T16:30:30",
      "IsDeleted": "undeleted",
      "SiteId": 1
    },
    {
      "Id": 5280,
      "Name": "volume",
      "ShowName": "当前卷册",
      "Type": "local",
      "ContentType": "ShortText",
      "DictKeyId": null,
      "Options": null,
      "IsMultiple": "no",
      "IsRepeat": "yes",
      "DataType": "ShortString",
      "BindDataField": "ShortString084",
      "Abbreviation": null,
      "Placeholder": null,
      "Unit": null,
      "Description": null,
      "SortOrder": 5280,
      "OperateAuthority": "create,edit,editShow,pagerShow",
      "IsRequired": "no",
      "DataSource": null,
      "DefaultValue": null,
      "IsSearch": "no",
      "IsUnifySearch": "no",
      "GroupType": "channel",
      "GroupId": 3123,
      "CreateIp": "127.0.0.1",
      "CreateBy": 172,
      "CreateTime": "2021-12-21T16:31:55",
      "IsDeleted": "undeleted",
      "SiteId": 1
    },
    {
      "Id": 5281,
      "Name": "readirection",
      "ShowName": "版式",
      "Type": "local",
      "ContentType": "ShortText",
      "DictKeyId": null,
      "Options": null,
      "IsMultiple": "no",
      "IsRepeat": "yes",
      "DataType": "ShortString",
      "BindDataField": "ShortString085",
      "Abbreviation": null,
      "Placeholder": null,
      "Unit": null,
      "Description": null,
      "SortOrder": 5281,
      "OperateAuthority": "create,edit,editShow",
      "IsRequired": "no",
      "DataSource": null,
      "DefaultValue": null,
      "IsSearch": "no",
      "IsUnifySearch": "no",
      "GroupType": "channel",
      "GroupId": 3123,
      "CreateIp": "127.0.0.1",
      "CreateBy": 172,
      "CreateTime": "2021-12-21T16:32:40",
      "IsDeleted": "undeleted",
      "SiteId": 1
    },
    {
      "Id": 5282,
      "Name": "booSize",
      "ShowName": "开本（单位：cm)",
      "Type": "local",
      "ContentType": "ShortText",
      "DictKeyId": null,
      "Options": null,
      "IsMultiple": "no",
      "IsRepeat": "yes",
      "DataType": "ShortString",
      "BindDataField": "ShortString086",
      "Abbreviation": null,
      "Placeholder": null,
      "Unit": null,
      "Description": null,
      "SortOrder": 5282,
      "OperateAuthority": "create,edit,editShow",
      "IsRequired": "no",
      "DataSource": null,
      "DefaultValue": null,
      "IsSearch": "no",
      "IsUnifySearch": "no",
      "GroupType": "channel",
      "GroupId": 3123,
      "CreateIp": "127.0.0.1",
      "CreateBy": 172,
      "CreateTime": "2021-12-21T16:33:26",
      "IsDeleted": "undeleted",
      "SiteId": 1
    },
    {
      "Id": 5283,
      "Name": "binding",
      "ShowName": "装帧",
      "Type": "local",
      "ContentType": "ShortText",
      "DictKeyId": null,
      "Options": null,
      "IsMultiple": "no",
      "IsRepeat": "yes",
      "DataType": "ShortString",
      "BindDataField": "ShortString087",
      "Abbreviation": null,
      "Placeholder": null,
      "Unit": null,
      "Description": null,
      "SortOrder": 5283,
      "OperateAuthority": "create,edit,editShow",
      "IsRequired": "no",
      "DataSource": null,
      "DefaultValue": null,
      "IsSearch": "no",
      "IsUnifySearch": "no",
      "GroupType": "channel",
      "GroupId": 3123,
      "CreateIp": "127.0.0.1",
      "CreateBy": 172,
      "CreateTime": "2021-12-21T16:34:19",
      "IsDeleted": "undeleted",
      "SiteId": 1
    },
    {
      "Id": 5284,
      "Name": "content",
      "ShowName": "内容提要",
      "Type": "local",
      "ContentType": "RichText",
      "DictKeyId": null,
      "Options": null,
      "IsMultiple": "no",
      "IsRepeat": "yes",
      "DataType": "Ntext",
      "BindDataField": "Ntext002",
      "Abbreviation": null,
      "Placeholder": null,
      "Unit": null,
      "Description": null,
      "SortOrder": 5284,
      "OperateAuthority": "create,edit,editShow",
      "IsRequired": "no",
      "DataSource": null,
      "DefaultValue": null,
      "IsSearch": "yes",
      "IsUnifySearch": "no",
      "GroupType": "channel",
      "GroupId": 3123,
      "CreateIp": "127.0.0.1",
      "CreateBy": 172,
      "CreateTime": "2021-12-21T16:35:55",
      "IsDeleted": "undeleted",
      "SiteId": 1
    },
    {
      "Id": 5285,
      "Name": "organs",
      "ShowName": "馆藏单位",
      "Type": "local",
      "ContentType": "ShortText",
      "DictKeyId": null,
      "Options": null,
      "IsMultiple": "no",
      "IsRepeat": "yes",
      "DataType": "ShortString",
      "BindDataField": "ShortString019",
      "Abbreviation": null,
      "Placeholder": null,
      "Unit": null,
      "Description": null,
      "SortOrder": 5285,
      "OperateAuthority": "create,edit,editShow",
      "IsRequired": "no",
      "DataSource": null,
      "DefaultValue": null,
      "IsSearch": "no",
      "IsUnifySearch": "no",
      "GroupType": "channel",
      "GroupId": 3123,
      "CreateIp": "127.0.0.1",
      "CreateBy": 172,
      "CreateTime": "2021-12-21T16:36:22",
      "IsDeleted": "undeleted",
      "SiteId": 1
    },
    {
      "Id": 5286,
      "Name": "location",
      "ShowName": "馆藏位置",
      "Type": "local",
      "ContentType": "MiddleText",
      "DictKeyId": null,
      "Options": null,
      "IsMultiple": "no",
      "IsRepeat": "yes",
      "DataType": "MiddleString",
      "BindDataField": "MiddleString008",
      "Abbreviation": null,
      "Placeholder": null,
      "Unit": null,
      "Description": null,
      "SortOrder": 5286,
      "OperateAuthority": "create,edit,editShow",
      "IsRequired": "no",
      "DataSource": null,
      "DefaultValue": null,
      "IsSearch": "no",
      "IsUnifySearch": "no",
      "GroupType": "channel",
      "GroupId": 3123,
      "CreateIp": "127.0.0.1",
      "CreateBy": 172,
      "CreateTime": "2021-12-21T16:37:13",
      "IsDeleted": "undeleted",
      "SiteId": 1
    },
    {
      "Id": 5287,
      "Name": "isRecommend",
      "ShowName": "是否推荐",
      "Type": "local",
      "ContentType": "Bit",
      "DictKeyId": null,
      "Options": null,
      "IsMultiple": "no",
      "IsRepeat": "yes",
      "DataType": "Bit",
      "BindDataField": "Bit003",
      "Abbreviation": null,
      "Placeholder": null,
      "Unit": null,
      "Description": null,
      "SortOrder": 5287,
      "OperateAuthority": "create,edit,editShow,pagerShow",
      "IsRequired": "yes",
      "DataSource": null,
      "DefaultValue": null,
      "IsSearch": "yes",
      "IsUnifySearch": "no",
      "GroupType": "channel",
      "GroupId": 3123,
      "CreateIp": "127.0.0.1",
      "CreateBy": 172,
      "CreateTime": "2021-12-21T16:41:38",
      "IsDeleted": "undeleted",
      "SiteId": 1
    },
    {
      "Id": 5288,
      "Name": "fullTextPath",
      "ShowName": "全文路径",
      "Type": "local",
      "ContentType": "MiddleText",
      "DictKeyId": null,
      "Options": null,
      "IsMultiple": "no",
      "IsRepeat": "yes",
      "DataType": "MiddleString",
      "BindDataField": "MiddleString015",
      "Abbreviation": null,
      "Placeholder": null,
      "Unit": null,
      "Description": null,
      "SortOrder": 5288,
      "OperateAuthority": "create,edit,editShow",
      "IsRequired": "no",
      "DataSource": null,
      "DefaultValue": null,
      "IsSearch": "no",
      "IsUnifySearch": "no",
      "GroupType": "channel",
      "GroupId": 3123,
      "CreateIp": "127.0.0.1",
      "CreateBy": 172,
      "CreateTime": "2021-12-22T09:07:17",
      "IsDeleted": "undeleted",
      "SiteId": 1
    },
    {
      "Id": 5290,
      "Name": "cover",
      "ShowName": "封面",
      "Type": "local",
      "ContentType": "ShortText",
      "DictKeyId": null,
      "Options": null,
      "IsMultiple": "no",
      "IsRepeat": "yes",
      "DataType": "ShortString",
      "BindDataField": "LongString002",
      "Abbreviation": null,
      "Placeholder": null,
      "Unit": null,
      "Description": null,
      "SortOrder": 5290,
      "OperateAuthority": "create,edit,editShow",
      "IsRequired": "no",
      "DataSource": null,
      "DefaultValue": null,
      "IsSearch": "no",
      "IsUnifySearch": "no",
      "GroupType": "channel",
      "GroupId": 3123,
      "CreateIp": "127.0.0.1",
      "CreateBy": 172,
      "CreateTime": "2021-12-23T08:52:33",
      "IsDeleted": "undeleted",
      "SiteId": 1
    }
  ],
  "detail": {
    "creator": "李明衡",
    "title": "医学五则",
    "author": "清廖云溪",
    "number": "294300307",
    "totalnum": "69314",
    "callnum": "371/2341",
    "docNo": "530000-2943-0000164",
    "class": "子部",
    "age": "清光绪十三年（1887）",
    "version": "刻本",
    "vol": null,
    "copiesCount": "五册",
    "volume": "第一册（医门初步）",
    "readirection": "10行22字小字双行22字白口四周单边",
    "booSize": "26.3×15.9",
    "binding": "线装",
    "content": null,
    "organs": null,
    "location": "1-2-1#1",
    "isRecommend": false,
    "fullTextPath": "294300307-1医学五则 医门初步 69314；294300307-2医学五则 药性简要三百首 69314；294300307-3医学五则 汤头歌括 69314；294300307-4医学五则 切縂伤寒 69314；294300307-5医学五则 增俌胍诀 69314",
    "cover": "\\D\\数据\\正确的古籍数据\\中医学院图书扫描\\4\\294300307医学五则69314\\294300307-1医学五则 医门初步 69314\\0259.jpg",
    "Id": 7296,
    "GroupType": "channel",
    "GroupId": 3123,
    "ViewCount": 69,
    "PraiseCount": 0,
    "CollectCount": 0,
    "DownCount": 0,
    "CreateIp": "127.0.0.1",
    "CreateBy": null,
    "CreateTime": null,
    "UpdateTime": "2023-06-21T10:18:53",
    "IsDeleted": "undeleted",
    "SiteId": 1
  },
  "fulltextpath": [
    {
      "name": "294300307-1医学五则 医门初步 69314",
      "tpath": "294300307-1医学五则 医门初步 69314",
      "IMAGES": [
        "http://guji.ynutcm.edu.cn/D/数据/正确的古籍数据/中医学院图书扫描/4/294300307医学五则69314/294300307-1医学五则 医门初步 69314/0259.jpg",
        "http://guji.ynutcm.edu.cn/D/数据/正确的古籍数据/中医学院图书扫描/4/294300307医学五则69314/294300307-1医学五则 医门初步 69314/0261.jpg",
        "http://guji.ynutcm.edu.cn/D/数据/正确的古籍数据/中医学院图书扫描/4/294300307医学五则69314/294300307-1医学五则 医门初步 69314/0263.jpg",
        "http://guji.ynutcm.edu.cn/D/数据/正确的古籍数据/中医学院图书扫描/4/294300307医学五则69314/294300307-1医学五则 医门初步 69314/0264.jpg",
        "http://guji.ynutcm.edu.cn/D/数据/正确的古籍数据/中医学院图书扫描/4/294300307医学五则69314/294300307-1医学五则 医门初步 69314/0266.jpg",
        "http://guji.ynutcm.edu.cn/D/数据/正确的古籍数据/中医学院图书扫描/4/294300307医学五则69314/294300307-1医学五则 医门初步 69314/0267.jpg",
        "http://guji.ynutcm.edu.cn/D/数据/正确的古籍数据/中医学院图书扫描/4/294300307医学五则69314/294300307-1医学五则 医门初步 69314/0268.jpg",
        "http://guji.ynutcm.edu.cn/D/数据/正确的古籍数据/中医学院图书扫描/4/294300307医学五则69314/294300307-1医学五则 医门初步 69314/0269.jpg",
        "http://guji.ynutcm.edu.cn/D/数据/正确的古籍数据/中医学院图书扫描/4/294300307医学五则69314/294300307-1医学五则 医门初步 69314/0270.jpg",
        "http://guji.ynutcm.edu.cn/D/数据/正确的古籍数据/中医学院图书扫描/4/294300307医学五则69314/294300307-1医学五则 医门初步 69314/0271.jpg",
        "http://guji.ynutcm.edu.cn/D/数据/正确的古籍数据/中医学院图书扫描/4/294300307医学五则69314/294300307-1医学五则 医门初步 69314/0272.jpg",
        "http://guji.ynutcm.edu.cn/D/数据/正确的古籍数据/中医学院图书扫描/4/294300307医学五则69314/294300307-1医学五则 医门初步 69314/0273.jpg",
        "http://guji.ynutcm.edu.cn/D/数据/正确的古籍数据/中医学院图书扫描/4/294300307医学五则69314/294300307-1医学五则 医门初步 69314/0274.jpg",
        "http://guji.ynutcm.edu.cn/D/数据/正确的古籍数据/中医学院图书扫描/4/294300307医学五则69314/294300307-1医学五则 医门初步 69314/0275.jpg",
        "http://guji.ynutcm.edu.cn/D/数据/正确的古籍数据/中医学院图书扫描/4/294300307医学五则69314/294300307-1医学五则 医门初步 69314/0276.jpg",
        "http://guji.ynutcm.edu.cn/D/数据/正确的古籍数据/中医学院图书扫描/4/294300307医学五则69314/294300307-1医学五则 医门初步 69314/0277.jpg",
        "http://guji.ynutcm.edu.cn/D/数据/正确的古籍数据/中医学院图书扫描/4/294300307医学五则69314/294300307-1医学五则 医门初步 69314/0278.jpg",
        "http://guji.ynutcm.edu.cn/D/数据/正确的古籍数据/中医学院图书扫描/4/294300307医学五则69314/294300307-1医学五则 医门初步 69314/0279.jpg",
        "http://guji.ynutcm.edu.cn/D/数据/正确的古籍数据/中医学院图书扫描/4/294300307医学五则69314/294300307-1医学五则 医门初步 69314/0280.jpg",
        "http://guji.ynutcm.edu.cn/D/数据/正确的古籍数据/中医学院图书扫描/4/294300307医学五则69314/294300307-1医学五则 医门初步 69314/0281.jpg",
        "http://guji.ynutcm.edu.cn/D/数据/正确的古籍数据/中医学院图书扫描/4/294300307医学五则69314/294300307-1医学五则 医门初步 69314/0282.jpg",
        "http://guji.ynutcm.edu.cn/D/数据/正确的古籍数据/中医学院图书扫描/4/294300307医学五则69314/294300307-1医学五则 医门初步 69314/0283.jpg",
        "http://guji.ynutcm.edu.cn/D/数据/正确的古籍数据/中医学院图书扫描/4/294300307医学五则69314/294300307-1医学五则 医门初步 69314/0284.jpg",
        "http://guji.ynutcm.edu.cn/D/数据/正确的古籍数据/中医学院图书扫描/4/294300307医学五则69314/294300307-1医学五则 医门初步 69314/0285.jpg",
        "http://guji.ynutcm.edu.cn/D/数据/正确的古籍数据/中医学院图书扫描/4/294300307医学五则69314/294300307-1医学五则 医门初步 69314/0286.jpg",
        "http://guji.ynutcm.edu.cn/D/数据/正确的古籍数据/中医学院图书扫描/4/294300307医学五则69314/294300307-1医学五则 医门初步 69314/0287.jpg",
        "http://guji.ynutcm.edu.cn/D/数据/正确的古籍数据/中医学院图书扫描/4/294300307医学五则69314/294300307-1医学五则 医门初步 69314/0288.jpg",
        "http://guji.ynutcm.edu.cn/D/数据/正确的古籍数据/中医学院图书扫描/4/294300307医学五则69314/294300307-1医学五则 医门初步 69314/0289.jpg",
        "http://guji.ynutcm.edu.cn/D/数据/正确的古籍数据/中医学院图书扫描/4/294300307医学五则69314/294300307-1医学五则 医门初步 69314/0290.jpg",
        "http://guji.ynutcm.edu.cn/D/数据/正确的古籍数据/中医学院图书扫描/4/294300307医学五则69314/294300307-1医学五则 医门初步 69314/0291.jpg",
        "http://guji.ynutcm.edu.cn/D/数据/正确的古籍数据/中医学院图书扫描/4/294300307医学五则69314/294300307-1医学五则 医门初步 69314/0292.jpg",
        "http://guji.ynutcm.edu.cn/D/数据/正确的古籍数据/中医学院图书扫描/4/294300307医学五则69314/294300307-1医学五则 医门初步 69314/0293.jpg",
        "http://guji.ynutcm.edu.cn/D/数据/正确的古籍数据/中医学院图书扫描/4/294300307医学五则69314/294300307-1医学五则 医门初步 69314/0294.jpg",
        "http://guji.ynutcm.edu.cn/D/数据/正确的古籍数据/中医学院图书扫描/4/294300307医学五则69314/294300307-1医学五则 医门初步 69314/0295.jpg",
        "http://guji.ynutcm.edu.cn/D/数据/正确的古籍数据/中医学院图书扫描/4/294300307医学五则69314/294300307-1医学五则 医门初步 69314/0296.jpg",
        "http://guji.ynutcm.edu.cn/D/数据/正确的古籍数据/中医学院图书扫描/4/294300307医学五则69314/294300307-1医学五则 医门初步 69314/0297.jpg",
        "http://guji.ynutcm.edu.cn/D/数据/正确的古籍数据/中医学院图书扫描/4/294300307医学五则69314/294300307-1医学五则 医门初步 69314/0298.jpg",
        "http://guji.ynutcm.edu.cn/D/数据/正确的古籍数据/中医学院图书扫描/4/294300307医学五则69314/294300307-1医学五则 医门初步 69314/0299.jpg",
        "http://guji.ynutcm.edu.cn/D/数据/正确的古籍数据/中医学院图书扫描/4/294300307医学五则69314/294300307-1医学五则 医门初步 69314/0300.jpg",
        "http://guji.ynutcm.edu.cn/D/数据/正确的古籍数据/中医学院图书扫描/4/294300307医学五则69314/294300307-1医学五则 医门初步 69314/0301.jpg",
        "http://guji.ynutcm.edu.cn/D/数据/正确的古籍数据/中医学院图书扫描/4/294300307医学五则69314/294300307-1医学五则 医门初步 69314/0302.jpg",
        "http://guji.ynutcm.edu.cn/D/数据/正确的古籍数据/中医学院图书扫描/4/294300307医学五则69314/294300307-1医学五则 医门初步 69314/0303.jpg",
        "http://guji.ynutcm.edu.cn/D/数据/正确的古籍数据/中医学院图书扫描/4/294300307医学五则69314/294300307-1医学五则 医门初步 69314/0304.jpg",
        "http://guji.ynutcm.edu.cn/D/数据/正确的古籍数据/中医学院图书扫描/4/294300307医学五则69314/294300307-1医学五则 医门初步 69314/0305.jpg",
        "http://guji.ynutcm.edu.cn/D/数据/正确的古籍数据/中医学院图书扫描/4/294300307医学五则69314/294300307-1医学五则 医门初步 69314/0306.jpg",
        "http://guji.ynutcm.edu.cn/D/数据/正确的古籍数据/中医学院图书扫描/4/294300307医学五则69314/294300307-1医学五则 医门初步 69314/0307.jpg",
        "http://guji.ynutcm.edu.cn/D/数据/正确的古籍数据/中医学院图书扫描/4/294300307医学五则69314/294300307-1医学五则 医门初步 69314/0308.jpg",
        "http://guji.ynutcm.edu.cn/D/数据/正确的古籍数据/中医学院图书扫描/4/294300307医学五则69314/294300307-1医学五则 医门初步 69314/0309.jpg",
        "http://guji.ynutcm.edu.cn/D/数据/正确的古籍数据/中医学院图书扫描/4/294300307医学五则69314/294300307-1医学五则 医门初步 69314/0310.jpg",
        "http://guji.ynutcm.edu.cn/D/数据/正确的古籍数据/中医学院图书扫描/4/294300307医学五则69314/294300307-1医学五则 医门初步 69314/0311.jpg",
        "http://guji.ynutcm.edu.cn/D/数据/正确的古籍数据/中医学院图书扫描/4/294300307医学五则69314/294300307-1医学五则 医门初步 69314/0312.jpg",
        "http://guji.ynutcm.edu.cn/D/数据/正确的古籍数据/中医学院图书扫描/4/294300307医学五则69314/294300307-1医学五则 医门初步 69314/0313.jpg",
        "http://guji.ynutcm.edu.cn/D/数据/正确的古籍数据/中医学院图书扫描/4/294300307医学五则69314/294300307-1医学五则 医门初步 69314/0314.jpg",
        "http://guji.ynutcm.edu.cn/D/数据/正确的古籍数据/中医学院图书扫描/4/294300307医学五则69314/294300307-1医学五则 医门初步 69314/0315.jpg",
        "http://guji.ynutcm.edu.cn/D/数据/正确的古籍数据/中医学院图书扫描/4/294300307医学五则69314/294300307-1医学五则 医门初步 69314/0316.jpg"
      ]
    },
    {
      "name": "294300307-2医学五则 药性简要三百首 69314",
      "tpath": "294300307-2医学五则 药性简要三百首 69314",
      "IMAGES": [
        "http://guji.ynutcm.edu.cn/D/数据/正确的古籍数据/中医学院图书扫描/4/294300307医学五则69314/294300307-2医学五则 药性简要三百首 69314/0069.jpg",
        "http://guji.ynutcm.edu.cn/D/数据/正确的古籍数据/中医学院图书扫描/4/294300307医学五则69314/294300307-2医学五则 药性简要三百首 69314/0070.jpg",
        "http://guji.ynutcm.edu.cn/D/数据/正确的古籍数据/中医学院图书扫描/4/294300307医学五则69314/294300307-2医学五则 药性简要三百首 69314/0071.jpg",
        "http://guji.ynutcm.edu.cn/D/数据/正确的古籍数据/中医学院图书扫描/4/294300307医学五则69314/294300307-2医学五则 药性简要三百首 69314/0072.jpg",
        "http://guji.ynutcm.edu.cn/D/数据/正确的古籍数据/中医学院图书扫描/4/294300307医学五则69314/294300307-2医学五则 药性简要三百首 69314/0073.jpg",
        "http://guji.ynutcm.edu.cn/D/数据/正确的古籍数据/中医学院图书扫描/4/294300307医学五则69314/294300307-2医学五则 药性简要三百首 69314/0074.jpg",
        "http://guji.ynutcm.edu.cn/D/数据/正确的古籍数据/中医学院图书扫描/4/294300307医学五则69314/294300307-2医学五则 药性简要三百首 69314/0075.jpg",
        "http://guji.ynutcm.edu.cn/D/数据/正确的古籍数据/中医学院图书扫描/4/294300307医学五则69314/294300307-2医学五则 药性简要三百首 69314/0076.jpg",
        "http://guji.ynutcm.edu.cn/D/数据/正确的古籍数据/中医学院图书扫描/4/294300307医学五则69314/294300307-2医学五则 药性简要三百首 69314/0077.jpg",
        "http://guji.ynutcm.edu.cn/D/数据/正确的古籍数据/中医学院图书扫描/4/294300307医学五则69314/294300307-2医学五则 药性简要三百首 69314/0078.jpg",
        "http://guji.ynutcm.edu.cn/D/数据/正确的古籍数据/中医学院图书扫描/4/294300307医学五则69314/294300307-2医学五则 药性简要三百首 69314/0079.jpg",
        "http://guji.ynutcm.edu.cn/D/数据/正确的古籍数据/中医学院图书扫描/4/294300307医学五则69314/294300307-2医学五则 药性简要三百首 69314/0080.jpg",
        "http://guji.ynutcm.edu.cn/D/数据/正确的古籍数据/中医学院图书扫描/4/294300307医学五则69314/294300307-2医学五则 药性简要三百首 69314/0081.jpg",
        "http://guji.ynutcm.edu.cn/D/数据/正确的古籍数据/中医学院图书扫描/4/294300307医学五则69314/294300307-2医学五则 药性简要三百首 69314/0082.jpg",
        "http://guji.ynutcm.edu.cn/D/数据/正确的古籍数据/中医学院图书扫描/4/294300307医学五则69314/294300307-2医学五则 药性简要三百首 69314/0083.jpg",
        "http://guji.ynutcm.edu.cn/D/数据/正确的古籍数据/中医学院图书扫描/4/294300307医学五则69314/294300307-2医学五则 药性简要三百首 69314/0084.jpg",
        "http://guji.ynutcm.edu.cn/D/数据/正确的古籍数据/中医学院图书扫描/4/294300307医学五则69314/294300307-2医学五则 药性简要三百首 69314/0085.jpg",
        "http://guji.ynutcm.edu.cn/D/数据/正确的古籍数据/中医学院图书扫描/4/294300307医学五则69314/294300307-2医学五则 药性简要三百首 69314/0086.jpg",
        "http://guji.ynutcm.edu.cn/D/数据/正确的古籍数据/中医学院图书扫描/4/294300307医学五则69314/294300307-2医学五则 药性简要三百首 69314/0087.jpg",
        "http://guji.ynutcm.edu.cn/D/数据/正确的古籍数据/中医学院图书扫描/4/294300307医学五则69314/294300307-2医学五则 药性简要三百首 69314/0088.jpg",
        "http://guji.ynutcm.edu.cn/D/数据/正确的古籍数据/中医学院图书扫描/4/294300307医学五则69314/294300307-2医学五则 药性简要三百首 69314/0089.jpg",
        "http://guji.ynutcm.edu.cn/D/数据/正确的古籍数据/中医学院图书扫描/4/294300307医学五则69314/294300307-2医学五则 药性简要三百首 69314/0090.jpg",
        "http://guji.ynutcm.edu.cn/D/数据/正确的古籍数据/中医学院图书扫描/4/294300307医学五则69314/294300307-2医学五则 药性简要三百首 69314/0091.jpg",
        "http://guji.ynutcm.edu.cn/D/数据/正确的古籍数据/中医学院图书扫描/4/294300307医学五则69314/294300307-2医学五则 药性简要三百首 69314/0093.jpg",
        "http://guji.ynutcm.edu.cn/D/数据/正确的古籍数据/中医学院图书扫描/4/294300307医学五则69314/294300307-2医学五则 药性简要三百首 69314/0094.jpg",
        "http://guji.ynutcm.edu.cn/D/数据/正确的古籍数据/中医学院图书扫描/4/294300307医学五则69314/294300307-2医学五则 药性简要三百首 69314/0095.jpg",
        "http://guji.ynutcm.edu.cn/D/数据/正确的古籍数据/中医学院图书扫描/4/294300307医学五则69314/294300307-2医学五则 药性简要三百首 69314/0096.jpg",
        "http://guji.ynutcm.edu.cn/D/数据/正确的古籍数据/中医学院图书扫描/4/294300307医学五则69314/294300307-2医学五则 药性简要三百首 69314/0097.jpg",
        "http://guji.ynutcm.edu.cn/D/数据/正确的古籍数据/中医学院图书扫描/4/294300307医学五则69314/294300307-2医学五则 药性简要三百首 69314/0098.jpg",
        "http://guji.ynutcm.edu.cn/D/数据/正确的古籍数据/中医学院图书扫描/4/294300307医学五则69314/294300307-2医学五则 药性简要三百首 69314/0099.jpg",
        "http://guji.ynutcm.edu.cn/D/数据/正确的古籍数据/中医学院图书扫描/4/294300307医学五则69314/294300307-2医学五则 药性简要三百首 69314/0100.jpg",
        "http://guji.ynutcm.edu.cn/D/数据/正确的古籍数据/中医学院图书扫描/4/294300307医学五则69314/294300307-2医学五则 药性简要三百首 69314/0101.jpg",
        "http://guji.ynutcm.edu.cn/D/数据/正确的古籍数据/中医学院图书扫描/4/294300307医学五则69314/294300307-2医学五则 药性简要三百首 69314/0102.jpg",
        "http://guji.ynutcm.edu.cn/D/数据/正确的古籍数据/中医学院图书扫描/4/294300307医学五则69314/294300307-2医学五则 药性简要三百首 69314/0103.jpg",
        "http://guji.ynutcm.edu.cn/D/数据/正确的古籍数据/中医学院图书扫描/4/294300307医学五则69314/294300307-2医学五则 药性简要三百首 69314/0104.jpg",
        "http://guji.ynutcm.edu.cn/D/数据/正确的古籍数据/中医学院图书扫描/4/294300307医学五则69314/294300307-2医学五则 药性简要三百首 69314/0105.jpg",
        "http://guji.ynutcm.edu.cn/D/数据/正确的古籍数据/中医学院图书扫描/4/294300307医学五则69314/294300307-2医学五则 药性简要三百首 69314/0106.jpg",
        "http://guji.ynutcm.edu.cn/D/数据/正确的古籍数据/中医学院图书扫描/4/294300307医学五则69314/294300307-2医学五则 药性简要三百首 69314/0107.jpg",
        "http://guji.ynutcm.edu.cn/D/数据/正确的古籍数据/中医学院图书扫描/4/294300307医学五则69314/294300307-2医学五则 药性简要三百首 69314/0108.jpg",
        "http://guji.ynutcm.edu.cn/D/数据/正确的古籍数据/中医学院图书扫描/4/294300307医学五则69314/294300307-2医学五则 药性简要三百首 69314/0111.jpg",
        "http://guji.ynutcm.edu.cn/D/数据/正确的古籍数据/中医学院图书扫描/4/294300307医学五则69314/294300307-2医学五则 药性简要三百首 69314/0112.jpg",
        "http://guji.ynutcm.edu.cn/D/数据/正确的古籍数据/中医学院图书扫描/4/294300307医学五则69314/294300307-2医学五则 药性简要三百首 69314/0113.jpg",
        "http://guji.ynutcm.edu.cn/D/数据/正确的古籍数据/中医学院图书扫描/4/294300307医学五则69314/294300307-2医学五则 药性简要三百首 69314/0114.jpg",
        "http://guji.ynutcm.edu.cn/D/数据/正确的古籍数据/中医学院图书扫描/4/294300307医学五则69314/294300307-2医学五则 药性简要三百首 69314/0115.jpg",
        "http://guji.ynutcm.edu.cn/D/数据/正确的古籍数据/中医学院图书扫描/4/294300307医学五则69314/294300307-2医学五则 药性简要三百首 69314/0116.jpg",
        "http://guji.ynutcm.edu.cn/D/数据/正确的古籍数据/中医学院图书扫描/4/294300307医学五则69314/294300307-2医学五则 药性简要三百首 69314/0117.jpg",
        "http://guji.ynutcm.edu.cn/D/数据/正确的古籍数据/中医学院图书扫描/4/294300307医学五则69314/294300307-2医学五则 药性简要三百首 69314/0118.jpg",
        "http://guji.ynutcm.edu.cn/D/数据/正确的古籍数据/中医学院图书扫描/4/294300307医学五则69314/294300307-2医学五则 药性简要三百首 69314/0119.jpg",
        "http://guji.ynutcm.edu.cn/D/数据/正确的古籍数据/中医学院图书扫描/4/294300307医学五则69314/294300307-2医学五则 药性简要三百首 69314/0120.jpg",
        "http://guji.ynutcm.edu.cn/D/数据/正确的古籍数据/中医学院图书扫描/4/294300307医学五则69314/294300307-2医学五则 药性简要三百首 69314/0121.jpg",
        "http://guji.ynutcm.edu.cn/D/数据/正确的古籍数据/中医学院图书扫描/4/294300307医学五则69314/294300307-2医学五则 药性简要三百首 69314/0122.jpg",
        "http://guji.ynutcm.edu.cn/D/数据/正确的古籍数据/中医学院图书扫描/4/294300307医学五则69314/294300307-2医学五则 药性简要三百首 69314/0123.jpg",
        "http://guji.ynutcm.edu.cn/D/数据/正确的古籍数据/中医学院图书扫描/4/294300307医学五则69314/294300307-2医学五则 药性简要三百首 69314/0124.jpg",
        "http://guji.ynutcm.edu.cn/D/数据/正确的古籍数据/中医学院图书扫描/4/294300307医学五则69314/294300307-2医学五则 药性简要三百首 69314/0125.jpg",
        "http://guji.ynutcm.edu.cn/D/数据/正确的古籍数据/中医学院图书扫描/4/294300307医学五则69314/294300307-2医学五则 药性简要三百首 69314/0126.jpg",
        "http://guji.ynutcm.edu.cn/D/数据/正确的古籍数据/中医学院图书扫描/4/294300307医学五则69314/294300307-2医学五则 药性简要三百首 69314/0127.jpg",
        "http://guji.ynutcm.edu.cn/D/数据/正确的古籍数据/中医学院图书扫描/4/294300307医学五则69314/294300307-2医学五则 药性简要三百首 69314/0128.jpg",
        "http://guji.ynutcm.edu.cn/D/数据/正确的古籍数据/中医学院图书扫描/4/294300307医学五则69314/294300307-2医学五则 药性简要三百首 69314/0129.jpg",
        "http://guji.ynutcm.edu.cn/D/数据/正确的古籍数据/中医学院图书扫描/4/294300307医学五则69314/294300307-2医学五则 药性简要三百首 69314/0130.jpg",
        "http://guji.ynutcm.edu.cn/D/数据/正确的古籍数据/中医学院图书扫描/4/294300307医学五则69314/294300307-2医学五则 药性简要三百首 69314/0131.jpg",
        "http://guji.ynutcm.edu.cn/D/数据/正确的古籍数据/中医学院图书扫描/4/294300307医学五则69314/294300307-2医学五则 药性简要三百首 69314/0132.jpg",
        "http://guji.ynutcm.edu.cn/D/数据/正确的古籍数据/中医学院图书扫描/4/294300307医学五则69314/294300307-2医学五则 药性简要三百首 69314/0133.jpg",
        "http://guji.ynutcm.edu.cn/D/数据/正确的古籍数据/中医学院图书扫描/4/294300307医学五则69314/294300307-2医学五则 药性简要三百首 69314/0134.jpg",
        "http://guji.ynutcm.edu.cn/D/数据/正确的古籍数据/中医学院图书扫描/4/294300307医学五则69314/294300307-2医学五则 药性简要三百首 69314/0135.jpg",
        "http://guji.ynutcm.edu.cn/D/数据/正确的古籍数据/中医学院图书扫描/4/294300307医学五则69314/294300307-2医学五则 药性简要三百首 69314/0136.jpg",
        "http://guji.ynutcm.edu.cn/D/数据/正确的古籍数据/中医学院图书扫描/4/294300307医学五则69314/294300307-2医学五则 药性简要三百首 69314/0137.jpg"
      ]
    },
    {
      "name": "294300307-3医学五则 汤头歌括 69314",
      "tpath": "294300307-3医学五则 汤头歌括 69314",
      "IMAGES": [
        "http://guji.ynutcm.edu.cn/D/数据/正确的古籍数据/中医学院图书扫描/4/294300307医学五则69314/294300307-3医学五则 汤头歌括 69314/0138.jpg",
        "http://guji.ynutcm.edu.cn/D/数据/正确的古籍数据/中医学院图书扫描/4/294300307医学五则69314/294300307-3医学五则 汤头歌括 69314/0139.jpg",
        "http://guji.ynutcm.edu.cn/D/数据/正确的古籍数据/中医学院图书扫描/4/294300307医学五则69314/294300307-3医学五则 汤头歌括 69314/0140.jpg",
        "http://guji.ynutcm.edu.cn/D/数据/正确的古籍数据/中医学院图书扫描/4/294300307医学五则69314/294300307-3医学五则 汤头歌括 69314/0141.jpg",
        "http://guji.ynutcm.edu.cn/D/数据/正确的古籍数据/中医学院图书扫描/4/294300307医学五则69314/294300307-3医学五则 汤头歌括 69314/0142.jpg",
        "http://guji.ynutcm.edu.cn/D/数据/正确的古籍数据/中医学院图书扫描/4/294300307医学五则69314/294300307-3医学五则 汤头歌括 69314/0143.jpg",
        "http://guji.ynutcm.edu.cn/D/数据/正确的古籍数据/中医学院图书扫描/4/294300307医学五则69314/294300307-3医学五则 汤头歌括 69314/0144.jpg",
        "http://guji.ynutcm.edu.cn/D/数据/正确的古籍数据/中医学院图书扫描/4/294300307医学五则69314/294300307-3医学五则 汤头歌括 69314/0145.jpg",
        "http://guji.ynutcm.edu.cn/D/数据/正确的古籍数据/中医学院图书扫描/4/294300307医学五则69314/294300307-3医学五则 汤头歌括 69314/0146.jpg",
        "http://guji.ynutcm.edu.cn/D/数据/正确的古籍数据/中医学院图书扫描/4/294300307医学五则69314/294300307-3医学五则 汤头歌括 69314/0147.jpg",
        "http://guji.ynutcm.edu.cn/D/数据/正确的古籍数据/中医学院图书扫描/4/294300307医学五则69314/294300307-3医学五则 汤头歌括 69314/0148.jpg",
        "http://guji.ynutcm.edu.cn/D/数据/正确的古籍数据/中医学院图书扫描/4/294300307医学五则69314/294300307-3医学五则 汤头歌括 69314/0149.jpg",
        "http://guji.ynutcm.edu.cn/D/数据/正确的古籍数据/中医学院图书扫描/4/294300307医学五则69314/294300307-3医学五则 汤头歌括 69314/0150.jpg",
        "http://guji.ynutcm.edu.cn/D/数据/正确的古籍数据/中医学院图书扫描/4/294300307医学五则69314/294300307-3医学五则 汤头歌括 69314/0151.jpg",
        "http://guji.ynutcm.edu.cn/D/数据/正确的古籍数据/中医学院图书扫描/4/294300307医学五则69314/294300307-3医学五则 汤头歌括 69314/0152.jpg",
        "http://guji.ynutcm.edu.cn/D/数据/正确的古籍数据/中医学院图书扫描/4/294300307医学五则69314/294300307-3医学五则 汤头歌括 69314/0153.jpg",
        "http://guji.ynutcm.edu.cn/D/数据/正确的古籍数据/中医学院图书扫描/4/294300307医学五则69314/294300307-3医学五则 汤头歌括 69314/0154.jpg",
        "http://guji.ynutcm.edu.cn/D/数据/正确的古籍数据/中医学院图书扫描/4/294300307医学五则69314/294300307-3医学五则 汤头歌括 69314/0155.jpg",
        "http://guji.ynutcm.edu.cn/D/数据/正确的古籍数据/中医学院图书扫描/4/294300307医学五则69314/294300307-3医学五则 汤头歌括 69314/0156.jpg",
        "http://guji.ynutcm.edu.cn/D/数据/正确的古籍数据/中医学院图书扫描/4/294300307医学五则69314/294300307-3医学五则 汤头歌括 69314/0157.jpg",
        "http://guji.ynutcm.edu.cn/D/数据/正确的古籍数据/中医学院图书扫描/4/294300307医学五则69314/294300307-3医学五则 汤头歌括 69314/0158.jpg",
        "http://guji.ynutcm.edu.cn/D/数据/正确的古籍数据/中医学院图书扫描/4/294300307医学五则69314/294300307-3医学五则 汤头歌括 69314/0160.jpg",
        "http://guji.ynutcm.edu.cn/D/数据/正确的古籍数据/中医学院图书扫描/4/294300307医学五则69314/294300307-3医学五则 汤头歌括 69314/0161.jpg",
        "http://guji.ynutcm.edu.cn/D/数据/正确的古籍数据/中医学院图书扫描/4/294300307医学五则69314/294300307-3医学五则 汤头歌括 69314/0163.jpg",
        "http://guji.ynutcm.edu.cn/D/数据/正确的古籍数据/中医学院图书扫描/4/294300307医学五则69314/294300307-3医学五则 汤头歌括 69314/0164.jpg",
        "http://guji.ynutcm.edu.cn/D/数据/正确的古籍数据/中医学院图书扫描/4/294300307医学五则69314/294300307-3医学五则 汤头歌括 69314/0165.jpg",
        "http://guji.ynutcm.edu.cn/D/数据/正确的古籍数据/中医学院图书扫描/4/294300307医学五则69314/294300307-3医学五则 汤头歌括 69314/0169.jpg",
        "http://guji.ynutcm.edu.cn/D/数据/正确的古籍数据/中医学院图书扫描/4/294300307医学五则69314/294300307-3医学五则 汤头歌括 69314/0170.jpg",
        "http://guji.ynutcm.edu.cn/D/数据/正确的古籍数据/中医学院图书扫描/4/294300307医学五则69314/294300307-3医学五则 汤头歌括 69314/0171.jpg",
        "http://guji.ynutcm.edu.cn/D/数据/正确的古籍数据/中医学院图书扫描/4/294300307医学五则69314/294300307-3医学五则 汤头歌括 69314/0172.jpg",
        "http://guji.ynutcm.edu.cn/D/数据/正确的古籍数据/中医学院图书扫描/4/294300307医学五则69314/294300307-3医学五则 汤头歌括 69314/0173.jpg",
        "http://guji.ynutcm.edu.cn/D/数据/正确的古籍数据/中医学院图书扫描/4/294300307医学五则69314/294300307-3医学五则 汤头歌括 69314/0174.jpg",
        "http://guji.ynutcm.edu.cn/D/数据/正确的古籍数据/中医学院图书扫描/4/294300307医学五则69314/294300307-3医学五则 汤头歌括 69314/0175.jpg",
        "http://guji.ynutcm.edu.cn/D/数据/正确的古籍数据/中医学院图书扫描/4/294300307医学五则69314/294300307-3医学五则 汤头歌括 69314/0176.jpg",
        "http://guji.ynutcm.edu.cn/D/数据/正确的古籍数据/中医学院图书扫描/4/294300307医学五则69314/294300307-3医学五则 汤头歌括 69314/0177.jpg",
        "http://guji.ynutcm.edu.cn/D/数据/正确的古籍数据/中医学院图书扫描/4/294300307医学五则69314/294300307-3医学五则 汤头歌括 69314/0178.jpg",
        "http://guji.ynutcm.edu.cn/D/数据/正确的古籍数据/中医学院图书扫描/4/294300307医学五则69314/294300307-3医学五则 汤头歌括 69314/0179.jpg",
        "http://guji.ynutcm.edu.cn/D/数据/正确的古籍数据/中医学院图书扫描/4/294300307医学五则69314/294300307-3医学五则 汤头歌括 69314/0180.jpg",
        "http://guji.ynutcm.edu.cn/D/数据/正确的古籍数据/中医学院图书扫描/4/294300307医学五则69314/294300307-3医学五则 汤头歌括 69314/0181.jpg",
        "http://guji.ynutcm.edu.cn/D/数据/正确的古籍数据/中医学院图书扫描/4/294300307医学五则69314/294300307-3医学五则 汤头歌括 69314/0182.jpg",
        "http://guji.ynutcm.edu.cn/D/数据/正确的古籍数据/中医学院图书扫描/4/294300307医学五则69314/294300307-3医学五则 汤头歌括 69314/0183.jpg",
        "http://guji.ynutcm.edu.cn/D/数据/正确的古籍数据/中医学院图书扫描/4/294300307医学五则69314/294300307-3医学五则 汤头歌括 69314/0184.jpg",
        "http://guji.ynutcm.edu.cn/D/数据/正确的古籍数据/中医学院图书扫描/4/294300307医学五则69314/294300307-3医学五则 汤头歌括 69314/0185.jpg",
        "http://guji.ynutcm.edu.cn/D/数据/正确的古籍数据/中医学院图书扫描/4/294300307医学五则69314/294300307-3医学五则 汤头歌括 69314/0186.jpg",
        "http://guji.ynutcm.edu.cn/D/数据/正确的古籍数据/中医学院图书扫描/4/294300307医学五则69314/294300307-3医学五则 汤头歌括 69314/0187.jpg",
        "http://guji.ynutcm.edu.cn/D/数据/正确的古籍数据/中医学院图书扫描/4/294300307医学五则69314/294300307-3医学五则 汤头歌括 69314/0188.jpg",
        "http://guji.ynutcm.edu.cn/D/数据/正确的古籍数据/中医学院图书扫描/4/294300307医学五则69314/294300307-3医学五则 汤头歌括 69314/0189.jpg",
        "http://guji.ynutcm.edu.cn/D/数据/正确的古籍数据/中医学院图书扫描/4/294300307医学五则69314/294300307-3医学五则 汤头歌括 69314/0190.jpg"
      ]
    },
    {
      "name": "294300307-4医学五则 切縂伤寒 69314",
      "tpath": "294300307-4医学五则 切縂伤寒 69314",
      "IMAGES": [
        "http://guji.ynutcm.edu.cn/D/数据/正确的古籍数据/中医学院图书扫描/4/294300307医学五则69314/294300307-4医学五则 切縂伤寒 69314/0001.jpg",
        "http://guji.ynutcm.edu.cn/D/数据/正确的古籍数据/中医学院图书扫描/4/294300307医学五则69314/294300307-4医学五则 切縂伤寒 69314/0002.jpg",
        "http://guji.ynutcm.edu.cn/D/数据/正确的古籍数据/中医学院图书扫描/4/294300307医学五则69314/294300307-4医学五则 切縂伤寒 69314/0003.jpg",
        "http://guji.ynutcm.edu.cn/D/数据/正确的古籍数据/中医学院图书扫描/4/294300307医学五则69314/294300307-4医学五则 切縂伤寒 69314/0004.jpg",
        "http://guji.ynutcm.edu.cn/D/数据/正确的古籍数据/中医学院图书扫描/4/294300307医学五则69314/294300307-4医学五则 切縂伤寒 69314/0005.jpg",
        "http://guji.ynutcm.edu.cn/D/数据/正确的古籍数据/中医学院图书扫描/4/294300307医学五则69314/294300307-4医学五则 切縂伤寒 69314/0006.jpg",
        "http://guji.ynutcm.edu.cn/D/数据/正确的古籍数据/中医学院图书扫描/4/294300307医学五则69314/294300307-4医学五则 切縂伤寒 69314/0007.jpg",
        "http://guji.ynutcm.edu.cn/D/数据/正确的古籍数据/中医学院图书扫描/4/294300307医学五则69314/294300307-4医学五则 切縂伤寒 69314/0008.jpg",
        "http://guji.ynutcm.edu.cn/D/数据/正确的古籍数据/中医学院图书扫描/4/294300307医学五则69314/294300307-4医学五则 切縂伤寒 69314/0009.jpg",
        "http://guji.ynutcm.edu.cn/D/数据/正确的古籍数据/中医学院图书扫描/4/294300307医学五则69314/294300307-4医学五则 切縂伤寒 69314/0010.jpg",
        "http://guji.ynutcm.edu.cn/D/数据/正确的古籍数据/中医学院图书扫描/4/294300307医学五则69314/294300307-4医学五则 切縂伤寒 69314/0011.jpg",
        "http://guji.ynutcm.edu.cn/D/数据/正确的古籍数据/中医学院图书扫描/4/294300307医学五则69314/294300307-4医学五则 切縂伤寒 69314/0012.jpg",
        "http://guji.ynutcm.edu.cn/D/数据/正确的古籍数据/中医学院图书扫描/4/294300307医学五则69314/294300307-4医学五则 切縂伤寒 69314/0013.jpg",
        "http://guji.ynutcm.edu.cn/D/数据/正确的古籍数据/中医学院图书扫描/4/294300307医学五则69314/294300307-4医学五则 切縂伤寒 69314/0014.jpg",
        "http://guji.ynutcm.edu.cn/D/数据/正确的古籍数据/中医学院图书扫描/4/294300307医学五则69314/294300307-4医学五则 切縂伤寒 69314/0015.jpg",
        "http://guji.ynutcm.edu.cn/D/数据/正确的古籍数据/中医学院图书扫描/4/294300307医学五则69314/294300307-4医学五则 切縂伤寒 69314/0016.jpg",
        "http://guji.ynutcm.edu.cn/D/数据/正确的古籍数据/中医学院图书扫描/4/294300307医学五则69314/294300307-4医学五则 切縂伤寒 69314/0017.jpg",
        "http://guji.ynutcm.edu.cn/D/数据/正确的古籍数据/中医学院图书扫描/4/294300307医学五则69314/294300307-4医学五则 切縂伤寒 69314/0018.jpg",
        "http://guji.ynutcm.edu.cn/D/数据/正确的古籍数据/中医学院图书扫描/4/294300307医学五则69314/294300307-4医学五则 切縂伤寒 69314/0019.jpg",
        "http://guji.ynutcm.edu.cn/D/数据/正确的古籍数据/中医学院图书扫描/4/294300307医学五则69314/294300307-4医学五则 切縂伤寒 69314/0020.jpg",
        "http://guji.ynutcm.edu.cn/D/数据/正确的古籍数据/中医学院图书扫描/4/294300307医学五则69314/294300307-4医学五则 切縂伤寒 69314/0021.jpg",
        "http://guji.ynutcm.edu.cn/D/数据/正确的古籍数据/中医学院图书扫描/4/294300307医学五则69314/294300307-4医学五则 切縂伤寒 69314/0022.jpg",
        "http://guji.ynutcm.edu.cn/D/数据/正确的古籍数据/中医学院图书扫描/4/294300307医学五则69314/294300307-4医学五则 切縂伤寒 69314/0023.jpg",
        "http://guji.ynutcm.edu.cn/D/数据/正确的古籍数据/中医学院图书扫描/4/294300307医学五则69314/294300307-4医学五则 切縂伤寒 69314/0024.jpg",
        "http://guji.ynutcm.edu.cn/D/数据/正确的古籍数据/中医学院图书扫描/4/294300307医学五则69314/294300307-4医学五则 切縂伤寒 69314/0025.jpg",
        "http://guji.ynutcm.edu.cn/D/数据/正确的古籍数据/中医学院图书扫描/4/294300307医学五则69314/294300307-4医学五则 切縂伤寒 69314/0026.jpg",
        "http://guji.ynutcm.edu.cn/D/数据/正确的古籍数据/中医学院图书扫描/4/294300307医学五则69314/294300307-4医学五则 切縂伤寒 69314/0027.jpg",
        "http://guji.ynutcm.edu.cn/D/数据/正确的古籍数据/中医学院图书扫描/4/294300307医学五则69314/294300307-4医学五则 切縂伤寒 69314/0028.jpg",
        "http://guji.ynutcm.edu.cn/D/数据/正确的古籍数据/中医学院图书扫描/4/294300307医学五则69314/294300307-4医学五则 切縂伤寒 69314/0029.jpg",
        "http://guji.ynutcm.edu.cn/D/数据/正确的古籍数据/中医学院图书扫描/4/294300307医学五则69314/294300307-4医学五则 切縂伤寒 69314/0030.jpg",
        "http://guji.ynutcm.edu.cn/D/数据/正确的古籍数据/中医学院图书扫描/4/294300307医学五则69314/294300307-4医学五则 切縂伤寒 69314/0031.jpg",
        "http://guji.ynutcm.edu.cn/D/数据/正确的古籍数据/中医学院图书扫描/4/294300307医学五则69314/294300307-4医学五则 切縂伤寒 69314/0032.jpg",
        "http://guji.ynutcm.edu.cn/D/数据/正确的古籍数据/中医学院图书扫描/4/294300307医学五则69314/294300307-4医学五则 切縂伤寒 69314/0033.jpg",
        "http://guji.ynutcm.edu.cn/D/数据/正确的古籍数据/中医学院图书扫描/4/294300307医学五则69314/294300307-4医学五则 切縂伤寒 69314/0034.jpg",
        "http://guji.ynutcm.edu.cn/D/数据/正确的古籍数据/中医学院图书扫描/4/294300307医学五则69314/294300307-4医学五则 切縂伤寒 69314/0035.jpg",
        "http://guji.ynutcm.edu.cn/D/数据/正确的古籍数据/中医学院图书扫描/4/294300307医学五则69314/294300307-4医学五则 切縂伤寒 69314/0036.jpg",
        "http://guji.ynutcm.edu.cn/D/数据/正确的古籍数据/中医学院图书扫描/4/294300307医学五则69314/294300307-4医学五则 切縂伤寒 69314/0037.jpg",
        "http://guji.ynutcm.edu.cn/D/数据/正确的古籍数据/中医学院图书扫描/4/294300307医学五则69314/294300307-4医学五则 切縂伤寒 69314/0038.jpg",
        "http://guji.ynutcm.edu.cn/D/数据/正确的古籍数据/中医学院图书扫描/4/294300307医学五则69314/294300307-4医学五则 切縂伤寒 69314/0039.jpg",
        "http://guji.ynutcm.edu.cn/D/数据/正确的古籍数据/中医学院图书扫描/4/294300307医学五则69314/294300307-4医学五则 切縂伤寒 69314/0040.jpg",
        "http://guji.ynutcm.edu.cn/D/数据/正确的古籍数据/中医学院图书扫描/4/294300307医学五则69314/294300307-4医学五则 切縂伤寒 69314/0041.jpg",
        "http://guji.ynutcm.edu.cn/D/数据/正确的古籍数据/中医学院图书扫描/4/294300307医学五则69314/294300307-4医学五则 切縂伤寒 69314/0042.jpg",
        "http://guji.ynutcm.edu.cn/D/数据/正确的古籍数据/中医学院图书扫描/4/294300307医学五则69314/294300307-4医学五则 切縂伤寒 69314/0043.jpg",
        "http://guji.ynutcm.edu.cn/D/数据/正确的古籍数据/中医学院图书扫描/4/294300307医学五则69314/294300307-4医学五则 切縂伤寒 69314/0044.jpg",
        "http://guji.ynutcm.edu.cn/D/数据/正确的古籍数据/中医学院图书扫描/4/294300307医学五则69314/294300307-4医学五则 切縂伤寒 69314/0045.jpg",
        "http://guji.ynutcm.edu.cn/D/数据/正确的古籍数据/中医学院图书扫描/4/294300307医学五则69314/294300307-4医学五则 切縂伤寒 69314/0046.jpg",
        "http://guji.ynutcm.edu.cn/D/数据/正确的古籍数据/中医学院图书扫描/4/294300307医学五则69314/294300307-4医学五则 切縂伤寒 69314/0047.jpg",
        "http://guji.ynutcm.edu.cn/D/数据/正确的古籍数据/中医学院图书扫描/4/294300307医学五则69314/294300307-4医学五则 切縂伤寒 69314/0048.jpg",
        "http://guji.ynutcm.edu.cn/D/数据/正确的古籍数据/中医学院图书扫描/4/294300307医学五则69314/294300307-4医学五则 切縂伤寒 69314/0049.jpg",
        "http://guji.ynutcm.edu.cn/D/数据/正确的古籍数据/中医学院图书扫描/4/294300307医学五则69314/294300307-4医学五则 切縂伤寒 69314/0050.jpg",
        "http://guji.ynutcm.edu.cn/D/数据/正确的古籍数据/中医学院图书扫描/4/294300307医学五则69314/294300307-4医学五则 切縂伤寒 69314/0051.jpg",
        "http://guji.ynutcm.edu.cn/D/数据/正确的古籍数据/中医学院图书扫描/4/294300307医学五则69314/294300307-4医学五则 切縂伤寒 69314/0052.jpg",
        "http://guji.ynutcm.edu.cn/D/数据/正确的古籍数据/中医学院图书扫描/4/294300307医学五则69314/294300307-4医学五则 切縂伤寒 69314/0053.jpg",
        "http://guji.ynutcm.edu.cn/D/数据/正确的古籍数据/中医学院图书扫描/4/294300307医学五则69314/294300307-4医学五则 切縂伤寒 69314/0054.jpg",
        "http://guji.ynutcm.edu.cn/D/数据/正确的古籍数据/中医学院图书扫描/4/294300307医学五则69314/294300307-4医学五则 切縂伤寒 69314/0055.jpg",
        "http://guji.ynutcm.edu.cn/D/数据/正确的古籍数据/中医学院图书扫描/4/294300307医学五则69314/294300307-4医学五则 切縂伤寒 69314/0056.jpg",
        "http://guji.ynutcm.edu.cn/D/数据/正确的古籍数据/中医学院图书扫描/4/294300307医学五则69314/294300307-4医学五则 切縂伤寒 69314/0057.jpg",
        "http://guji.ynutcm.edu.cn/D/数据/正确的古籍数据/中医学院图书扫描/4/294300307医学五则69314/294300307-4医学五则 切縂伤寒 69314/0058.jpg",
        "http://guji.ynutcm.edu.cn/D/数据/正确的古籍数据/中医学院图书扫描/4/294300307医学五则69314/294300307-4医学五则 切縂伤寒 69314/0059.jpg",
        "http://guji.ynutcm.edu.cn/D/数据/正确的古籍数据/中医学院图书扫描/4/294300307医学五则69314/294300307-4医学五则 切縂伤寒 69314/0060.jpg",
        "http://guji.ynutcm.edu.cn/D/数据/正确的古籍数据/中医学院图书扫描/4/294300307医学五则69314/294300307-4医学五则 切縂伤寒 69314/0061.jpg",
        "http://guji.ynutcm.edu.cn/D/数据/正确的古籍数据/中医学院图书扫描/4/294300307医学五则69314/294300307-4医学五则 切縂伤寒 69314/0062.jpg",
        "http://guji.ynutcm.edu.cn/D/数据/正确的古籍数据/中医学院图书扫描/4/294300307医学五则69314/294300307-4医学五则 切縂伤寒 69314/0063.jpg",
        "http://guji.ynutcm.edu.cn/D/数据/正确的古籍数据/中医学院图书扫描/4/294300307医学五则69314/294300307-4医学五则 切縂伤寒 69314/0064.jpg",
        "http://guji.ynutcm.edu.cn/D/数据/正确的古籍数据/中医学院图书扫描/4/294300307医学五则69314/294300307-4医学五则 切縂伤寒 69314/0065.jpg",
        "http://guji.ynutcm.edu.cn/D/数据/正确的古籍数据/中医学院图书扫描/4/294300307医学五则69314/294300307-4医学五则 切縂伤寒 69314/0066.jpg",
        "http://guji.ynutcm.edu.cn/D/数据/正确的古籍数据/中医学院图书扫描/4/294300307医学五则69314/294300307-4医学五则 切縂伤寒 69314/0067.jpg",
        "http://guji.ynutcm.edu.cn/D/数据/正确的古籍数据/中医学院图书扫描/4/294300307医学五则69314/294300307-4医学五则 切縂伤寒 69314/0068.jpg"
      ]
    },
    {
      "name": "294300307-5医学五则 增俌胍诀 69314",
      "tpath": "294300307-5医学五则 增俌胍诀 69314",
      "IMAGES": [
        "http://guji.ynutcm.edu.cn/D/数据/正确的古籍数据/中医学院图书扫描/4/294300307医学五则69314/294300307-5医学五则 增俌胍诀 69314/0191.jpg",
        "http://guji.ynutcm.edu.cn/D/数据/正确的古籍数据/中医学院图书扫描/4/294300307医学五则69314/294300307-5医学五则 增俌胍诀 69314/0192.jpg",
        "http://guji.ynutcm.edu.cn/D/数据/正确的古籍数据/中医学院图书扫描/4/294300307医学五则69314/294300307-5医学五则 增俌胍诀 69314/0193.jpg",
        "http://guji.ynutcm.edu.cn/D/数据/正确的古籍数据/中医学院图书扫描/4/294300307医学五则69314/294300307-5医学五则 增俌胍诀 69314/0194.jpg",
        "http://guji.ynutcm.edu.cn/D/数据/正确的古籍数据/中医学院图书扫描/4/294300307医学五则69314/294300307-5医学五则 增俌胍诀 69314/0195.jpg",
        "http://guji.ynutcm.edu.cn/D/数据/正确的古籍数据/中医学院图书扫描/4/294300307医学五则69314/294300307-5医学五则 增俌胍诀 69314/0196.jpg",
        "http://guji.ynutcm.edu.cn/D/数据/正确的古籍数据/中医学院图书扫描/4/294300307医学五则69314/294300307-5医学五则 增俌胍诀 69314/0197.jpg",
        "http://guji.ynutcm.edu.cn/D/数据/正确的古籍数据/中医学院图书扫描/4/294300307医学五则69314/294300307-5医学五则 增俌胍诀 69314/0198.jpg",
        "http://guji.ynutcm.edu.cn/D/数据/正确的古籍数据/中医学院图书扫描/4/294300307医学五则69314/294300307-5医学五则 增俌胍诀 69314/0199.jpg",
        "http://guji.ynutcm.edu.cn/D/数据/正确的古籍数据/中医学院图书扫描/4/294300307医学五则69314/294300307-5医学五则 增俌胍诀 69314/0200.jpg",
        "http://guji.ynutcm.edu.cn/D/数据/正确的古籍数据/中医学院图书扫描/4/294300307医学五则69314/294300307-5医学五则 增俌胍诀 69314/0201.jpg",
        "http://guji.ynutcm.edu.cn/D/数据/正确的古籍数据/中医学院图书扫描/4/294300307医学五则69314/294300307-5医学五则 增俌胍诀 69314/0202.jpg",
        "http://guji.ynutcm.edu.cn/D/数据/正确的古籍数据/中医学院图书扫描/4/294300307医学五则69314/294300307-5医学五则 增俌胍诀 69314/0203.jpg",
        "http://guji.ynutcm.edu.cn/D/数据/正确的古籍数据/中医学院图书扫描/4/294300307医学五则69314/294300307-5医学五则 增俌胍诀 69314/0204.jpg",
        "http://guji.ynutcm.edu.cn/D/数据/正确的古籍数据/中医学院图书扫描/4/294300307医学五则69314/294300307-5医学五则 增俌胍诀 69314/0205.jpg",
        "http://guji.ynutcm.edu.cn/D/数据/正确的古籍数据/中医学院图书扫描/4/294300307医学五则69314/294300307-5医学五则 增俌胍诀 69314/0206.jpg",
        "http://guji.ynutcm.edu.cn/D/数据/正确的古籍数据/中医学院图书扫描/4/294300307医学五则69314/294300307-5医学五则 增俌胍诀 69314/0207.jpg",
        "http://guji.ynutcm.edu.cn/D/数据/正确的古籍数据/中医学院图书扫描/4/294300307医学五则69314/294300307-5医学五则 增俌胍诀 69314/0208.jpg",
        "http://guji.ynutcm.edu.cn/D/数据/正确的古籍数据/中医学院图书扫描/4/294300307医学五则69314/294300307-5医学五则 增俌胍诀 69314/0209.jpg",
        "http://guji.ynutcm.edu.cn/D/数据/正确的古籍数据/中医学院图书扫描/4/294300307医学五则69314/294300307-5医学五则 增俌胍诀 69314/0210.jpg",
        "http://guji.ynutcm.edu.cn/D/数据/正确的古籍数据/中医学院图书扫描/4/294300307医学五则69314/294300307-5医学五则 增俌胍诀 69314/0211.jpg",
        "http://guji.ynutcm.edu.cn/D/数据/正确的古籍数据/中医学院图书扫描/4/294300307医学五则69314/294300307-5医学五则 增俌胍诀 69314/0212.jpg",
        "http://guji.ynutcm.edu.cn/D/数据/正确的古籍数据/中医学院图书扫描/4/294300307医学五则69314/294300307-5医学五则 增俌胍诀 69314/0213.jpg",
        "http://guji.ynutcm.edu.cn/D/数据/正确的古籍数据/中医学院图书扫描/4/294300307医学五则69314/294300307-5医学五则 增俌胍诀 69314/0214.jpg",
        "http://guji.ynutcm.edu.cn/D/数据/正确的古籍数据/中医学院图书扫描/4/294300307医学五则69314/294300307-5医学五则 增俌胍诀 69314/0215.jpg",
        "http://guji.ynutcm.edu.cn/D/数据/正确的古籍数据/中医学院图书扫描/4/294300307医学五则69314/294300307-5医学五则 增俌胍诀 69314/0216.jpg",
        "http://guji.ynutcm.edu.cn/D/数据/正确的古籍数据/中医学院图书扫描/4/294300307医学五则69314/294300307-5医学五则 增俌胍诀 69314/0217.jpg",
        "http://guji.ynutcm.edu.cn/D/数据/正确的古籍数据/中医学院图书扫描/4/294300307医学五则69314/294300307-5医学五则 增俌胍诀 69314/0218.jpg",
        "http://guji.ynutcm.edu.cn/D/数据/正确的古籍数据/中医学院图书扫描/4/294300307医学五则69314/294300307-5医学五则 增俌胍诀 69314/0219.jpg",
        "http://guji.ynutcm.edu.cn/D/数据/正确的古籍数据/中医学院图书扫描/4/294300307医学五则69314/294300307-5医学五则 增俌胍诀 69314/0220.jpg",
        "http://guji.ynutcm.edu.cn/D/数据/正确的古籍数据/中医学院图书扫描/4/294300307医学五则69314/294300307-5医学五则 增俌胍诀 69314/0221.jpg",
        "http://guji.ynutcm.edu.cn/D/数据/正确的古籍数据/中医学院图书扫描/4/294300307医学五则69314/294300307-5医学五则 增俌胍诀 69314/0222.jpg",
        "http://guji.ynutcm.edu.cn/D/数据/正确的古籍数据/中医学院图书扫描/4/294300307医学五则69314/294300307-5医学五则 增俌胍诀 69314/0223.jpg",
        "http://guji.ynutcm.edu.cn/D/数据/正确的古籍数据/中医学院图书扫描/4/294300307医学五则69314/294300307-5医学五则 增俌胍诀 69314/0224.jpg",
        "http://guji.ynutcm.edu.cn/D/数据/正确的古籍数据/中医学院图书扫描/4/294300307医学五则69314/294300307-5医学五则 增俌胍诀 69314/0225.jpg",
        "http://guji.ynutcm.edu.cn/D/数据/正确的古籍数据/中医学院图书扫描/4/294300307医学五则69314/294300307-5医学五则 增俌胍诀 69314/0226.jpg",
        "http://guji.ynutcm.edu.cn/D/数据/正确的古籍数据/中医学院图书扫描/4/294300307医学五则69314/294300307-5医学五则 增俌胍诀 69314/0227.jpg",
        "http://guji.ynutcm.edu.cn/D/数据/正确的古籍数据/中医学院图书扫描/4/294300307医学五则69314/294300307-5医学五则 增俌胍诀 69314/0228.jpg",
        "http://guji.ynutcm.edu.cn/D/数据/正确的古籍数据/中医学院图书扫描/4/294300307医学五则69314/294300307-5医学五则 增俌胍诀 69314/0229.jpg",
        "http://guji.ynutcm.edu.cn/D/数据/正确的古籍数据/中医学院图书扫描/4/294300307医学五则69314/294300307-5医学五则 增俌胍诀 69314/0230.jpg",
        "http://guji.ynutcm.edu.cn/D/数据/正确的古籍数据/中医学院图书扫描/4/294300307医学五则69314/294300307-5医学五则 增俌胍诀 69314/0232.jpg",
        "http://guji.ynutcm.edu.cn/D/数据/正确的古籍数据/中医学院图书扫描/4/294300307医学五则69314/294300307-5医学五则 增俌胍诀 69314/0233.jpg",
        "http://guji.ynutcm.edu.cn/D/数据/正确的古籍数据/中医学院图书扫描/4/294300307医学五则69314/294300307-5医学五则 增俌胍诀 69314/0234.jpg",
        "http://guji.ynutcm.edu.cn/D/数据/正确的古籍数据/中医学院图书扫描/4/294300307医学五则69314/294300307-5医学五则 增俌胍诀 69314/0235.jpg",
        "http://guji.ynutcm.edu.cn/D/数据/正确的古籍数据/中医学院图书扫描/4/294300307医学五则69314/294300307-5医学五则 增俌胍诀 69314/0236.jpg",
        "http://guji.ynutcm.edu.cn/D/数据/正确的古籍数据/中医学院图书扫描/4/294300307医学五则69314/294300307-5医学五则 增俌胍诀 69314/0237.jpg",
        "http://guji.ynutcm.edu.cn/D/数据/正确的古籍数据/中医学院图书扫描/4/294300307医学五则69314/294300307-5医学五则 增俌胍诀 69314/0238.jpg",
        "http://guji.ynutcm.edu.cn/D/数据/正确的古籍数据/中医学院图书扫描/4/294300307医学五则69314/294300307-5医学五则 增俌胍诀 69314/0239.jpg",
        "http://guji.ynutcm.edu.cn/D/数据/正确的古籍数据/中医学院图书扫描/4/294300307医学五则69314/294300307-5医学五则 增俌胍诀 69314/0240.jpg",
        "http://guji.ynutcm.edu.cn/D/数据/正确的古籍数据/中医学院图书扫描/4/294300307医学五则69314/294300307-5医学五则 增俌胍诀 69314/0241.jpg",
        "http://guji.ynutcm.edu.cn/D/数据/正确的古籍数据/中医学院图书扫描/4/294300307医学五则69314/294300307-5医学五则 增俌胍诀 69314/0242.jpg",
        "http://guji.ynutcm.edu.cn/D/数据/正确的古籍数据/中医学院图书扫描/4/294300307医学五则69314/294300307-5医学五则 增俌胍诀 69314/0243.jpg",
        "http://guji.ynutcm.edu.cn/D/数据/正确的古籍数据/中医学院图书扫描/4/294300307医学五则69314/294300307-5医学五则 增俌胍诀 69314/0244.jpg",
        "http://guji.ynutcm.edu.cn/D/数据/正确的古籍数据/中医学院图书扫描/4/294300307医学五则69314/294300307-5医学五则 增俌胍诀 69314/0245.jpg",
        "http://guji.ynutcm.edu.cn/D/数据/正确的古籍数据/中医学院图书扫描/4/294300307医学五则69314/294300307-5医学五则 增俌胍诀 69314/0246.jpg",
        "http://guji.ynutcm.edu.cn/D/数据/正确的古籍数据/中医学院图书扫描/4/294300307医学五则69314/294300307-5医学五则 增俌胍诀 69314/0247.jpg",
        "http://guji.ynutcm.edu.cn/D/数据/正确的古籍数据/中医学院图书扫描/4/294300307医学五则69314/294300307-5医学五则 增俌胍诀 69314/0248.jpg",
        "http://guji.ynutcm.edu.cn/D/数据/正确的古籍数据/中医学院图书扫描/4/294300307医学五则69314/294300307-5医学五则 增俌胍诀 69314/0249.jpg",
        "http://guji.ynutcm.edu.cn/D/数据/正确的古籍数据/中医学院图书扫描/4/294300307医学五则69314/294300307-5医学五则 增俌胍诀 69314/0250.jpg",
        "http://guji.ynutcm.edu.cn/D/数据/正确的古籍数据/中医学院图书扫描/4/294300307医学五则69314/294300307-5医学五则 增俌胍诀 69314/0251.jpg",
        "http://guji.ynutcm.edu.cn/D/数据/正确的古籍数据/中医学院图书扫描/4/294300307医学五则69314/294300307-5医学五则 增俌胍诀 69314/0253.jpg",
        "http://guji.ynutcm.edu.cn/D/数据/正确的古籍数据/中医学院图书扫描/4/294300307医学五则69314/294300307-5医学五则 增俌胍诀 69314/0255.jpg",
        "http://guji.ynutcm.edu.cn/D/数据/正确的古籍数据/中医学院图书扫描/4/294300307医学五则69314/294300307-5医学五则 增俌胍诀 69314/0256.jpg",
        "http://guji.ynutcm.edu.cn/D/数据/正确的古籍数据/中医学院图书扫描/4/294300307医学五则69314/294300307-5医学五则 增俌胍诀 69314/0257.jpg",
        "http://guji.ynutcm.edu.cn/D/数据/正确的古籍数据/中医学院图书扫描/4/294300307医学五则69314/294300307-5医学五则 增俌胍诀 69314/0258.jpg"
      ]
    }
  ],
  "channel": {
    "Id": 3123,
    "ParentId": null,
    "Name": "古籍",
    "Unikey": "gj",
    "Module": "dataField,data",
    "CreateTempalte": null,
    "ListTemplate": "Pager_gj",
    "DetailTemplate": "Detail_gj",
    "CrawlWebIds": null,
    "ZtRule": null,
    "SortIndex": 3123,
    "SiteId": 1,
    "IsWork": "yes",
    "IsDeleted": "undeleted"
  },
  "isCollect": false,
  "aboutlist": [
    {
      "creator": "李明衡",
      "title": "医学五则",
      "author": [
        "清廖云溪"
      ],
      "number": "294300307",
      "totalnum": "69314",
      "callnum": "371/2341",
      "docNo": "530000-2943-0000164",
      "class": [
        "子部"
      ],
      "age": "清光绪十三年（1887）",
      "version": "刻本",
      "vol": null,
      "copiesCount": "五册",
      "volume": "第一册（医门初步）",
      "readirection": "10行22字小字双行22字白口四周单边",
      "booSize": "26.3×15.9",
      "binding": "线装",
      "content": null,
      "organs": null,
      "location": "1-2-1#1",
      "isRecommend": "false",
      "fullTextPath": "294300307-1医学五则 医门初步 69314；294300307-2医学五则 药性简要三百首 69314；294300307-3医学五则 汤头歌括 69314；294300307-4医学五则 切縂伤寒 69314；294300307-5医学五则 增俌胍诀 69314",
      "cover": "\\D\\数据\\正确的古籍数据\\中医学院图书扫描\\4\\294300307医学五则69314\\294300307-1医学五则 医门初步 69314\\0259.jpg",
      "Id": "7296",
      "GroupType": "channel",
      "GroupId": "3123",
      "ViewCount": 41,
      "PraiseCount": "0",
      "CollectCount": "0",
      "DownCount": "0",
      "CreateIp": "127.0.0.1",
      "CreateBy": null,
      "CreateTime": null,
      "UpdateTime": "2023-04-27T20:14:19",
      "IsDeleted": "undeleted",
      "SiteId": "1"
    }
  ]
}